frameworkk/__init__.py
frameworkk/api.py
frameworkk/middleware.py
frameworkk/orm.py
frameworkk/response.py
frameworkk-0.0.3.dist-info/METADATA
frameworkk-0.0.3.dist-info/WHEEL
frameworkk-0.0.3.dist-info/top_level.txt
frameworkk-0.0.3.dist-info/RECORD
